{"timestamp":"2025-10-14T10:00:00Z","device_id":"IOT-001","zone":"Zone-A","device_type":"temperature","value":72.3,"battery":95,"status":"active"}
{"timestamp":"2025-10-14T10:04:00Z","device_id":"IOT-002","zone":"Zone-A","device_type":"humidity","value":45.2,"battery":88,"status":"active"}
{"timestamp":"2025-10-14T10:08:00Z","device_id":"IOT-003","zone":"Zone-B","device_type":"temperature","value":68.7,"battery":92,"status":"active"}
{"timestamp":"2025-10-14T10:12:00Z","device_id":"IOT-004","zone":"Zone-B","device_type":"pressure","value":1013.2,"battery":85,"status":"active"}
{"timestamp":"2025-10-14T10:16:00Z","device_id":"IOT-005","zone":"Zone-C","device_type":"temperature","value":75.1,"battery":90,"status":"active"}
{"timestamp":"2025-10-14T10:20:00Z","device_id":"IOT-006","zone":"Zone-A","device_type":"humidity","value":48.5,"battery":87,"status":"active"}
{"timestamp":"2025-10-14T10:24:00Z","device_id":"IOT-007","zone":"Zone-B","device_type":"temperature","value":69.9,"battery":94,"status":"active"}
{"timestamp":"2025-10-14T10:28:00Z","device_id":"IOT-008","zone":"Zone-C","device_type":"pressure","value":1012.8,"battery":91,"status":"active"}
{"timestamp":"2025-10-14T10:32:00Z","device_id":"IOT-009","zone":"Zone-A","device_type":"temperature","value":73.2,"battery":89,"status":"active"}
{"timestamp":"2025-10-14T10:36:00Z","device_id":"IOT-010","zone":"Zone-B","device_type":"humidity","value":46.8,"battery":93,"status":"active"}
{"timestamp":"2025-10-14T10:40:00Z","device_id":"IOT-011","zone":"Zone-C","device_type":"temperature","value":71.5,"battery":86,"status":"active"}
{"timestamp":"2025-10-14T10:44:00Z","device_id":"IOT-012","zone":"Zone-A","device_type":"pressure","value":1014.1,"battery":88,"status":"active"}
{"timestamp":"2025-10-14T10:48:00Z","device_id":"IOT-013","zone":"Zone-B","device_type":"temperature","value":70.3,"battery":90,"status":"active"}
{"timestamp":"2025-10-14T10:52:00Z","device_id":"IOT-014","zone":"Zone-C","device_type":"humidity","value":44.9,"battery":92,"status":"active"}
{"timestamp":"2025-10-14T10:56:00Z","device_id":"IOT-015","zone":"Zone-A","device_type":"temperature","value":74.6,"battery":87,"status":"active"}
{"timestamp":"2025-10-14T10:58:00Z","device_id":"IOT-016","zone":"Zone-B","device_type":"pressure","value":1013.5,"battery":91,"status":"active"}
{"timestamp":"2025-10-14T10:59:00Z","device_id":"IOT-017","zone":"Zone-C","device_type":"temperature","value":72.8,"battery":89,"status":"active"}
{"timestamp":"2025-10-14T11:00:00Z","device_id":"IOT-018","zone":"Zone-A","device_type":"humidity","value":47.3,"battery":94,"status":"active"}
{"timestamp":"2025-10-14T11:04:00Z","device_id":"IOT-019","zone":"Zone-B","device_type":"temperature","value":69.2,"battery":88,"status":"active"}
{"timestamp":"2025-10-14T11:08:00Z","device_id":"IOT-020","zone":"Zone-C","device_type":"pressure","value":1012.3,"battery":90,"status":"active"}
{"timestamp":"2025-10-14T11:12:00Z","device_id":"IOT-021","zone":"Zone-A","device_type":"temperature","value":76.4,"battery":85,"status":"active"}
{"timestamp":"2025-10-14T11:16:00Z","device_id":"IOT-022","zone":"Zone-B","device_type":"humidity","value":49.1,"battery":92,"status":"active"}
{"timestamp":"2025-10-14T11:20:00Z","device_id":"IOT-023","zone":"Zone-C","device_type":"temperature","value":68.5,"battery":87,"status":"active"}
{"timestamp":"2025-10-14T11:24:00Z","device_id":"IOT-024","zone":"Zone-A","device_type":"pressure","value":1015.2,"battery":93,"status":"active"}
{"timestamp":"2025-10-14T11:28:00Z","device_id":"IOT-025","zone":"Zone-B","device_type":"temperature","value":71.7,"battery":86,"status":"active"}
{"timestamp":"2025-10-14T11:32:00Z","device_id":"IOT-026","zone":"Zone-C","device_type":"humidity","value":43.8,"battery":91,"status":"active"}
{"timestamp":"2025-10-14T11:36:00Z","device_id":"IOT-027","zone":"Zone-A","device_type":"temperature","value":73.9,"battery":89,"status":"active"}
{"timestamp":"2025-10-14T11:40:00Z","device_id":"IOT-028","zone":"Zone-B","device_type":"pressure","value":1013.9,"battery":94,"status":"active"}
{"timestamp":"2025-10-14T11:44:00Z","device_id":"IOT-029","zone":"Zone-C","device_type":"temperature","value":70.6,"battery":88,"status":"active"}
{"timestamp":"2025-10-14T11:48:00Z","device_id":"IOT-030","zone":"Zone-A","device_type":"humidity","value":46.2,"battery":90,"status":"active"}
{"timestamp":"2025-10-14T11:52:00Z","device_id":"IOT-031","zone":"Zone-B","device_type":"temperature","value":72.1,"battery":85,"status":"active"}
{"timestamp":"2025-10-14T11:56:00Z","device_id":"IOT-032","zone":"Zone-C","device_type":"pressure","value":1014.7,"battery":92,"status":"active"}
{"timestamp":"2025-10-14T11:58:00Z","device_id":"IOT-033","zone":"Zone-A","device_type":"temperature","value":75.3,"battery":87,"status":"active"}
{"timestamp":"2025-10-14T11:59:00Z","device_id":"IOT-034","zone":"Zone-B","device_type":"humidity","value":48.7,"battery":91,"status":"active"}
{"timestamp":"2025-10-14T12:00:00Z","device_id":"IOT-035","zone":"Zone-C","device_type":"temperature","value":69.4,"battery":89,"status":"active"}
{"timestamp":"2025-10-14T12:04:00Z","device_id":"IOT-036","zone":"Zone-A","device_type":"pressure","value":1012.6,"battery":93,"status":"active"}
{"timestamp":"2025-10-14T12:08:00Z","device_id":"IOT-037","zone":"Zone-B","device_type":"temperature","value":74.8,"battery":86,"status":"active"}
{"timestamp":"2025-10-14T12:12:00Z","device_id":"IOT-038","zone":"Zone-C","device_type":"humidity","value":45.6,"battery":90,"status":"active"}
{"timestamp":"2025-10-14T12:16:00Z","device_id":"IOT-039","zone":"Zone-A","device_type":"temperature","value":71.9,"battery":88,"status":"active"}
{"timestamp":"2025-10-14T12:20:00Z","device_id":"IOT-040","zone":"Zone-B","device_type":"pressure","value":1013.4,"battery":92,"status":"active"}
{"timestamp":"2025-10-14T12:24:00Z","device_id":"IOT-041","zone":"Zone-C","device_type":"temperature","value":73.6,"battery":85,"status":"active"}
{"timestamp":"2025-10-14T12:28:00Z","device_id":"IOT-042","zone":"Zone-A","device_type":"humidity","value":47.9,"battery":91,"status":"active"}
{"timestamp":"2025-10-14T12:32:00Z","device_id":"IOT-043","zone":"Zone-B","device_type":"temperature","value":68.8,"battery":87,"status":"active"}
{"timestamp":"2025-10-14T12:36:00Z","device_id":"IOT-044","zone":"Zone-C","device_type":"pressure","value":1014.9,"battery":94,"status":"active"}
{"timestamp":"2025-10-14T12:40:00Z","device_id":"IOT-045","zone":"Zone-A","device_type":"temperature","value":76.1,"battery":89,"status":"active"}
{"timestamp":"2025-10-14T12:44:00Z","device_id":"IOT-046","zone":"Zone-B","device_type":"humidity","value":44.3,"battery":90,"status":"active"}
{"timestamp":"2025-10-14T12:48:00Z","device_id":"IOT-047","zone":"Zone-C","device_type":"temperature","value":70.7,"battery":86,"status":"active"}
{"timestamp":"2025-10-14T12:52:00Z","device_id":"IOT-048","zone":"Zone-A","device_type":"pressure","value":1015.8,"battery":92,"status":"active"}
{"timestamp":"2025-10-14T12:56:00Z","device_id":"IOT-049","zone":"Zone-B","device_type":"temperature","value":72.4,"battery":88,"status":"active"}
{"timestamp":"2025-10-14T12:59:00Z","device_id":"IOT-050","zone":"Zone-C","device_type":"humidity","value":46.5,"battery":91,"status":"active"}
